[{"Index":0,"Value":"Daily Search Trends"},{"Index":1,"Value":"Milan vs Torino"},{"Index":2,"Value":"Real Madrid vs Al-Hilal"},{"Index":3,"Value":"Steven Spielberg"},{"Index":4,"Value":"PK Rosy"},{"Index":5,"Value":"Promise Day Quotes"},{"Index":6,"Value":"Al Nassr"},{"Index":7,"Value":"Primary TET Result"},{"Index":8,"Value":"Rajasthan Budget 2023"},{"Index":9,"Value":"Farzi Review"},{"Index":10,"Value":"Lithium"},{"Index":11,"Value":"ICC Women's T20 World Cup"},{"Index":12,"Value":"Fast X"},{"Index":13,"Value":"Amigos Movie review"},{"Index":14,"Value":"DaDa"},{"Index":15,"Value":"Hyderabad FC"},{"Index":16,"Value":"Your Place or Mine"},{"Index":17,"Value":"Sun"},{"Index":18,"Value":"रोहित शर्मा"},{"Index":19,"Value":"Calcutta High Court"},{"Index":20,"Value":"Aus vs Ind"}]