[{"Index":0,"Value":"Daily Search Trends"},{"Index":1,"Value":"Sabalenka"},{"Index":2,"Value":"Bengals vs Chiefs"},{"Index":3,"Value":"Preston vs Tottenham"},{"Index":4,"Value":"Barcelona"},{"Index":5,"Value":"Man City vs Arsenal"},{"Index":6,"Value":"Paul Pelosi"},{"Index":7,"Value":"FA Cup"},{"Index":8,"Value":"Royal Rumble 2023"},{"Index":9,"Value":"Eagles vs 49ers"},{"Index":10,"Value":"Jay Leno"},{"Index":11,"Value":"Jennifer Lopez"},{"Index":12,"Value":"Billy Packer"},{"Index":13,"Value":"Tua Tagovailoa"},{"Index":14,"Value":"Holocaust Remembrance Day 2023"},{"Index":15,"Value":"Lockwood and Co"},{"Index":16,"Value":"Giannis Antetokounmpo"},{"Index":17,"Value":"Intel stock"},{"Index":18,"Value":"Lil Yachty"},{"Index":19,"Value":"Clippers"},{"Index":20,"Value":"Timberwolves"}]