[{"Index":0,"Value":"Daily Search Trends"},{"Index":1,"Value":"Buzz Aldrin"},{"Index":2,"Value":"Cowboys vs 49ers"},{"Index":3,"Value":"Actor Julian Sands missing"},{"Index":4,"Value":"NBC"},{"Index":5,"Value":"Leicester City vs Brighton"},{"Index":6,"Value":"Mahomes injury"},{"Index":7,"Value":"Crystal Palace vs Newcastle"},{"Index":8,"Value":"Los Angeles Lakers"},{"Index":9,"Value":"WEST HAM vs EVERTON"},{"Index":10,"Value":"Duke basketball"},{"Index":11,"Value":"Sam Smith"},{"Index":12,"Value":"Juventus"},{"Index":13,"Value":"Southampton vs Aston Villa"},{"Index":14,"Value":"Chelsea"},{"Index":15,"Value":"Kylie Jenner"},{"Index":16,"Value":"Gwen Stefani"},{"Index":17,"Value":"Cleveland Cavaliers"},{"Index":18,"Value":"Russell Westbrook"},{"Index":19,"Value":"Kansas City Chiefs"},{"Index":20,"Value":"Eagles"}]