[{"Index":0,"Value":"Daily Search Trends"},{"Index":1,"Value":"India vs New Zealand 2023"},{"Index":2,"Value":"SSC MTS 2023"},{"Index":3,"Value":"Adani Enterprises share price"},{"Index":4,"Value":"Modi in Mumbai"},{"Index":5,"Value":"THU vs REN"},{"Index":6,"Value":"Man City vs Tottenham"},{"Index":7,"Value":"IndusInd Bank share price"},{"Index":8,"Value":"Taeyang"},{"Index":9,"Value":"Shakira"},{"Index":10,"Value":"Nanpakal Nerathu Mayakkam"},{"Index":11,"Value":"World population"},{"Index":12,"Value":"Climate activist Greta Thunberg"},{"Index":13,"Value":"IND vs NZ"},{"Index":14,"Value":"Cricket"},{"Index":15,"Value":"PSG vs Al Nassr"},{"Index":16,"Value":"Live Score"},{"Index":17,"Value":"Sports"},{"Index":18,"Value":"Crystal Palace vs Man United"},{"Index":19,"Value":"JEE Main"},{"Index":20,"Value":"ICC"}]