[{"Index":0,"Value":"Daily Search Trends"},{"Index":1,"Value":"Bobby Hull"},{"Index":2,"Value":"Tee Higgins"},{"Index":3,"Value":"Germaine Pratt"},{"Index":4,"Value":"Paramount"},{"Index":5,"Value":"Shania Twain"},{"Index":6,"Value":"Kyle Smaine"},{"Index":7,"Value":"Black History Month"},{"Index":8,"Value":"Lil Uzi Vert"},{"Index":9,"Value":"Bengals vs Chiefs"},{"Index":10,"Value":"49ers"},{"Index":11,"Value":"Super Bowl 2023"},{"Index":12,"Value":"Eagles"},{"Index":13,"Value":"Annie Wersching death"},{"Index":14,"Value":"Brandon Smiley"},{"Index":15,"Value":"Nick Offerman"},{"Index":16,"Value":"Lisa Loring"},{"Index":17,"Value":"Jason Kelce"},{"Index":18,"Value":"Real Madrid vs Real Sociedad"},{"Index":19,"Value":"Novak Djokovic"},{"Index":20,"Value":"Jimmy Garoppolo"}]