[{"Index":0,"Value":"Daily Search Trends"},{"Index":1,"Value":"RB Leipzig vs Bayern"},{"Index":2,"Value":"Hyderabad FC"},{"Index":3,"Value":"Mission Majnu"},{"Index":4,"Value":"Radhika Merchant"},{"Index":5,"Value":"Usain Bolt"},{"Index":6,"Value":"Bageshwar Dham news"},{"Index":7,"Value":"KVS Exam Date 2023"},{"Index":8,"Value":"Andy Murray"},{"Index":9,"Value":"IND vs NZ 2nd ODI"},{"Index":10,"Value":"When will JEE Main 2023 admit card release"},{"Index":11,"Value":"HUL share price"},{"Index":12,"Value":"Google Layoffs"},{"Index":13,"Value":"Rishi Sunak"},{"Index":14,"Value":"Trossard"},{"Index":15,"Value":"Alec Baldwin"},{"Index":16,"Value":"That '90s Show"},{"Index":17,"Value":"Michael Clarke"},{"Index":18,"Value":"PSG vs Al-Nassr"},{"Index":19,"Value":"Man City vs Tottenham"},{"Index":20,"Value":"Hockey World Cup 2023"}]