[{"Index":0,"Value":"Daily Search Trends"},{"Index":1,"Value":"Andy Murray"},{"Index":2,"Value":"Asian Paints Share Price"},{"Index":3,"Value":"Usain Bolt"},{"Index":4,"Value":"Trossard"},{"Index":5,"Value":"Shah Rukh Khan Pathaan"},{"Index":6,"Value":"That '90s Show"},{"Index":7,"Value":"Hockey World Cup 2023"},{"Index":8,"Value":"India Women vs South Africa Women"},{"Index":9,"Value":"Villarreal vs Real Madrid"},{"Index":10,"Value":"Man City vs Tottenham"},{"Index":11,"Value":"SSC MTS 2023"},{"Index":12,"Value":"MS Dhoni"},{"Index":13,"Value":"Modi in Mumbai"},{"Index":14,"Value":"Adani Enterprises share price"},{"Index":15,"Value":"Nanpakal Nerathu Mayakkam review"},{"Index":16,"Value":"BBC Documentary On Modi"},{"Index":17,"Value":"Brij Bhushan Sharan Singh"},{"Index":18,"Value":"Mumbai City FC"},{"Index":19,"Value":"Inter Milan"},{"Index":20,"Value":"Indusind bank share price"}]