[{"Index":0,"Value":"Daily Search Trends"},{"Index":1,"Value":"K Viswanath"},{"Index":2,"Value":"CA Foundation Result"},{"Index":3,"Value":"Michael movie Review"},{"Index":4,"Value":"Thalapathy 67 title"},{"Index":5,"Value":"JEE Mains Answer Key 2023"},{"Index":6,"Value":"Gautam Adani Group"},{"Index":7,"Value":"Ilhan Omar"},{"Index":8,"Value":"Chelsea vs Fulham"},{"Index":9,"Value":"Amul Milk Price"},{"Index":10,"Value":"Thunivu OTT release date"},{"Index":11,"Value":"Kerala Budget 2023"},{"Index":12,"Value":"World Cancer Day"},{"Index":13,"Value":"Divi's Lab Share"},{"Index":14,"Value":"Paulo Coelho"},{"Index":15,"Value":"IND W vs SA W"},{"Index":16,"Value":"IND vs AUS"},{"Index":17,"Value":"East Bengal vs Kerala Blasters"},{"Index":18,"Value":"Al Fateh vs al-nassr"},{"Index":19,"Value":"Real Madrid vs Valencia"},{"Index":20,"Value":"PSG"}]