[{"Index":0,"Value":"Daily Search Trends"},{"Index":1,"Value":"Buffalo earthquake"},{"Index":2,"Value":"Train derailment Ohio"},{"Index":3,"Value":"Hogwarts Legacy review"},{"Index":4,"Value":"Bob Marley"},{"Index":5,"Value":"Doja Cat"},{"Index":6,"Value":"Derek Carr"},{"Index":7,"Value":"Bad Bunny Grammys 2023"},{"Index":8,"Value":"NBA trade deadline"},{"Index":9,"Value":"Harriet Tubman"},{"Index":10,"Value":"The Rock"},{"Index":11,"Value":"Justin Rose"},{"Index":12,"Value":"STATE OF THE UNION 2023"},{"Index":13,"Value":"Kyrie Irving"},{"Index":14,"Value":"Turkey earthquake"},{"Index":15,"Value":"Harry Styles"},{"Index":16,"Value":"Sam Smith"},{"Index":17,"Value":"Pro Bowl 2023"},{"Index":18,"Value":"Tottenham"},{"Index":19,"Value":"Super Bowl"},{"Index":20,"Value":"Bonnie Raitt"}]