[{"Index":0,"Value":"Daily Search Trends"},{"Index":1,"Value":"CRPF Admit Card"},{"Index":2,"Value":"Barcelona vs Man United"},{"Index":3,"Value":"Arsenal vs Man City"},{"Index":4,"Value":"Chris Evans"},{"Index":5,"Value":"Chetan Sharma news"},{"Index":6,"Value":"Dortmund vs Chelsea"},{"Index":7,"Value":"Marburg virus"},{"Index":8,"Value":"Nikki Yadav"},{"Index":9,"Value":"Milan vs Tottenham"},{"Index":10,"Value":"CTET Answer Key"},{"Index":11,"Value":"Hardik Pandya"},{"Index":12,"Value":"BBC"},{"Index":13,"Value":"Javed Khan Amrohi"},{"Index":14,"Value":"Valentines Day gifts"},{"Index":15,"Value":"Cow Hug Day"},{"Index":16,"Value":"Airbus"},{"Index":17,"Value":"Liverpool"},{"Index":18,"Value":"Nikki Haley"},{"Index":19,"Value":"Dream Girl 2"},{"Index":20,"Value":"Why is Valentine's Day celebrated"}]