[{"Index":0,"Value":"Daily Search Trends"},{"Index":1,"Value":"Live Score"},{"Index":2,"Value":"Cricket"},{"Index":3,"Value":"Sports"},{"Index":4,"Value":"JEE Mains Admit Card 2023"},{"Index":5,"Value":"Southampton vs Aston Villa"},{"Index":6,"Value":"WEST HAM vs EVERTON"},{"Index":7,"Value":"Crystal Palace vs Newcastle"},{"Index":8,"Value":"ZIM vs IRE"},{"Index":9,"Value":"Novak Djokovic"},{"Index":10,"Value":"Juventus"},{"Index":11,"Value":"SSC MTS · 2023"},{"Index":12,"Value":"Buzz Aldrin"},{"Index":13,"Value":"Hyderabad FC"},{"Index":14,"Value":"Steve Smith"},{"Index":15,"Value":"IND vs NZ"},{"Index":16,"Value":"Liverpool vs Chelsea"},{"Index":17,"Value":"Chhatriwali"},{"Index":18,"Value":"Bageshwar Dham news"},{"Index":19,"Value":"Usain Bolt"},{"Index":20,"Value":"Real Madrid"}]