[{"Index":0,"Value":"Daily Search Trends"},{"Index":1,"Value":"David Crosby"},{"Index":2,"Value":"Man City vs Tottenham"},{"Index":3,"Value":"Warriors"},{"Index":4,"Value":"Miley Cyrus"},{"Index":5,"Value":"Lakers"},{"Index":6,"Value":"Anton Walkes"},{"Index":7,"Value":"Real Madrid"},{"Index":8,"Value":"Involuntary manslaughter"},{"Index":9,"Value":"Andy Murray"},{"Index":10,"Value":"Cristiano Ronaldo"},{"Index":11,"Value":"Supplemental nutrition assistance program"},{"Index":12,"Value":"Phoenix Suns"},{"Index":13,"Value":"Debt ceiling"},{"Index":14,"Value":"Stephen Curry"},{"Index":15,"Value":"Leslie Jordan"},{"Index":16,"Value":"Chicago Bulls"},{"Index":17,"Value":"Taco Bell rat poisoning"},{"Index":18,"Value":"Ted Lasso season 3"},{"Index":19,"Value":"Netflix stock"},{"Index":20,"Value":"Young Thug"}]