[{"Index":0,"Value":"Daily Search Trends"},{"Index":1,"Value":"Richard Belzer"},{"Index":2,"Value":"Man United vs Leicester City"},{"Index":3,"Value":"PSG"},{"Index":4,"Value":"TOTTENHAM vs WEST HAM"},{"Index":5,"Value":"Barcelona vs Cádiz"},{"Index":6,"Value":"UNC basketball"},{"Index":7,"Value":"Jon Rahm"},{"Index":8,"Value":"Guns N' Roses"},{"Index":9,"Value":"Temple University"},{"Index":10,"Value":"Jimmy Carter"},{"Index":11,"Value":"Daytona 500"},{"Index":12,"Value":"Aston Villa vs Arsenal"},{"Index":13,"Value":"XFL"},{"Index":14,"Value":"Elimination Chamber 2023"},{"Index":15,"Value":"Rosalynn Carter"},{"Index":16,"Value":"Christian Atsu"},{"Index":17,"Value":"3-Point Contest 2023"},{"Index":18,"Value":"Kevin Love"},{"Index":19,"Value":"Dolly Parton"},{"Index":20,"Value":"Liverpool"}]