[{"Index":0,"Value":"Daily Search Trends"},{"Index":1,"Value":"CTET Answer Key"},{"Index":2,"Value":"Milan vs Tottenham"},{"Index":3,"Value":"BBC"},{"Index":4,"Value":"Valentines Day gifts"},{"Index":5,"Value":"Javed Khan Amrohi"},{"Index":6,"Value":"Cow Hug Day"},{"Index":7,"Value":"Liverpool"},{"Index":8,"Value":"Pulwama"},{"Index":9,"Value":"Dream Girl 2"},{"Index":10,"Value":"Why is Valentine's Day celebrated"},{"Index":11,"Value":"Hardik Pandya Marriage"},{"Index":12,"Value":"KAR vs PES"},{"Index":13,"Value":"Nikki Haley"},{"Index":14,"Value":"Airbus"},{"Index":15,"Value":"U.S inflation data"},{"Index":16,"Value":"Valentine's Day"},{"Index":17,"Value":"PSG vs Bayern"},{"Index":18,"Value":"MC Stan"},{"Index":19,"Value":"WPL Auction"},{"Index":20,"Value":"Super Bowl"}]