[{"Index":0,"Value":"Daily Search Trends"},{"Index":1,"Value":"Napoli vs Juventus"},{"Index":2,"Value":"Aston Villa vs Leeds United"},{"Index":3,"Value":"Steven Spielberg"},{"Index":4,"Value":"PAK vs NZ ODI"},{"Index":5,"Value":"STR vs HEA"},{"Index":6,"Value":"Thom Browne"},{"Index":7,"Value":"Divita Rai Miss Universe"},{"Index":8,"Value":"LIC AAO notification 2023"},{"Index":9,"Value":"David Warner"},{"Index":10,"Value":"Bayern Munich"},{"Index":11,"Value":"Hockey World Cup 2023"},{"Index":12,"Value":"Elvis Presley"},{"Index":13,"Value":"Barcelona"},{"Index":14,"Value":"Kanye West"},{"Index":15,"Value":"Chelsea"},{"Index":16,"Value":"Waltair Veerayya reviews"},{"Index":17,"Value":"Paytm share price"},{"Index":18,"Value":"Trial By Fire"},{"Index":19,"Value":"शरद यादव"},{"Index":20,"Value":"Veera Simha Reddy collections"}]