[{"Index":0,"Value":"Daily Search Trends"},{"Index":1,"Value":"SA vs ENG"},{"Index":2,"Value":"UPSC"},{"Index":3,"Value":"Wakanda Forever"},{"Index":4,"Value":"BUDGET 2023 In Hindi"},{"Index":5,"Value":"UPSC form Date 2023"},{"Index":6,"Value":"Comet C/2022 E3"},{"Index":7,"Value":"Andhra Pradesh"},{"Index":8,"Value":"Adani Enterprises"},{"Index":9,"Value":"Harry Styles"},{"Index":10,"Value":"Enzo Fernandez"},{"Index":11,"Value":"Citadel"},{"Index":12,"Value":"Samsung S23"},{"Index":13,"Value":"Credit Suisse"},{"Index":14,"Value":"BTS: Yet to Come in Cinemas"},{"Index":15,"Value":"ITC"},{"Index":16,"Value":"Budget 2023"},{"Index":17,"Value":"IND vs NZ 3rd T20"},{"Index":18,"Value":"Economic Survey 2023"},{"Index":19,"Value":"Marcel Sabitzer"},{"Index":20,"Value":"Asaram Bapu"}]