[{"Index":0,"Value":"Daily Search Trends"},{"Index":1,"Value":"Buzz Aldrin"},{"Index":2,"Value":"Cowboys"},{"Index":3,"Value":"Liverpool vs Chelsea"},{"Index":4,"Value":"Actor Julian Sands missing"},{"Index":5,"Value":"Daniel Jones"},{"Index":6,"Value":"NBC"},{"Index":7,"Value":"Sam Smith"},{"Index":8,"Value":"Kylie Jenner"},{"Index":9,"Value":"Crystal Palace vs Newcastle"},{"Index":10,"Value":"WEST HAM vs EVERTON"},{"Index":11,"Value":"Saquon Barkley"},{"Index":12,"Value":"Juventus"},{"Index":13,"Value":"Gwen Stefani"},{"Index":14,"Value":"DeVonta Smith"},{"Index":15,"Value":"Cleveland Cavaliers"},{"Index":16,"Value":"Tony Dungy tweet"},{"Index":17,"Value":"Kansas City Chiefs"},{"Index":18,"Value":"Eagles"},{"Index":19,"Value":"Lakers"},{"Index":20,"Value":"Tyre Nichols"}]