[{"Index":0,"Value":"Daily Search Trends"},{"Index":1,"Value":"Rohit Sharma"},{"Index":2,"Value":"Milan vs Inter"},{"Index":3,"Value":"MS Dhoni"},{"Index":4,"Value":"Shubman Gill"},{"Index":5,"Value":"Cricket"},{"Index":6,"Value":"Sports"},{"Index":7,"Value":"Crystal Palace vs Man United"},{"Index":8,"Value":"ICC"},{"Index":9,"Value":"Mohammed Siraj"},{"Index":10,"Value":"Al Nassr vs PSG"},{"Index":11,"Value":"Rafael Nadal"},{"Index":12,"Value":"Prime Minister"},{"Index":13,"Value":"JEE Main"},{"Index":14,"Value":"Liverpool"},{"Index":15,"Value":"Arvind Kejriwal"},{"Index":16,"Value":"Greta Thunberg"},{"Index":17,"Value":"Bengaluru FC"},{"Index":18,"Value":"Microsoft layoffs"},{"Index":19,"Value":"Vinesh Phogat"},{"Index":20,"Value":"Jeemain.nta.nic.in admit card"}]