[{"Index":0,"Value":"Daily Search Trends"},{"Index":1,"Value":"Ind vs Ire Women's"},{"Index":2,"Value":"Cheteshwar Pujara"},{"Index":3,"Value":"Ligue 1"},{"Index":4,"Value":"MSBTE result"},{"Index":5,"Value":"Goa"},{"Index":6,"Value":"Bharatiya Janata Party"},{"Index":7,"Value":"Kartik Aaryan Shehzada"},{"Index":8,"Value":"Cipla share price"},{"Index":9,"Value":"The Last of Us' Episode 6"},{"Index":10,"Value":"Lionel Messi"},{"Index":11,"Value":"Ritesh Agarwal"},{"Index":12,"Value":"Dragon Ball"},{"Index":13,"Value":"PSG"},{"Index":14,"Value":"Barcelona vs Cádiz"},{"Index":15,"Value":"Mayilsamy"},{"Index":16,"Value":"Tottenham vs West Ham"},{"Index":17,"Value":"Mayilsamy actor"},{"Index":18,"Value":"Ant-Man \u0026 the Wasp: Quantumania"},{"Index":19,"Value":"Taraka Ratna news"},{"Index":20,"Value":"Man United vs Leicester City"}]